chalk/Chalk.py
chalk/SupportedColor.py
chalk/__init__.py
nodechalk-0.2.0.dist-info/LICENSE
nodechalk-0.2.0.dist-info/METADATA
nodechalk-0.2.0.dist-info/WHEEL
nodechalk-0.2.0.dist-info/top_level.txt
nodechalk-0.2.0.dist-info/RECORD
